[
  { "id": 1, "name": "POTATOES", "category": "Vegetables", "price": 15, "image": "https://res.cloudinary.com/dfqqacmzv/image/upload/v1760772725/s1_pb7gr0.png" },
  { "id": 2, "name": "ONION", "category": "Vegetables", "price": 36, "image": "https://res.cloudinary.com/dfqqacmzv/image/upload/v1760772725/s2_p0ajad.png" },
  { "id": 3, "name": "TOMATOES", "category": "Vegetables", "price": 24, "image": "https://res.cloudinary.com/dfqqacmzv/image/upload/v1760772725/s3_f3dtue.png" },
  { "id": 4, "name": "CHILLI", "category": "Vegetables", "price": 45, "image": "https://res.cloudinary.com/dfqqacmzv/image/upload/v1760772726/s4_kc5n0r.png" },
  { "id": 5, "name": "BEETROOT", "category": "Vegetables", "price": 32, "image": "https://res.cloudinary.com/dfqqacmzv/image/upload/v1760772726/s5_o71mfr.png" },
  { "id": 6, "name": "YAM", "category": "Vegetables", "price": 38, "image": "https://res.cloudinary.com/dfqqacmzv/image/upload/v1760772726/s6_diaza3.png" },
  { "id": 7, "name": "GARLIC", "category": "Vegetables", "price": 95, "image": "https://res.cloudinary.com/dfqqacmzv/image/upload/v1760772725/s7_m75kfz.png" },
  { "id": 8, "name": "FRENCH BEANS", "category": "Vegetables", "price": 60, "image": "https://res.cloudinary.com/dfqqacmzv/image/upload/v1760772725/s8_ahjxir.png" },
  { "id": 9, "name": "LADY FINGER", "category": "Vegetables", "price": 37, "image": "https://res.cloudinary.com/dfqqacmzv/image/upload/v1760772726/s9_aowpny.png" },
  { "id": 10, "name": "GREEN PEAS", "category": "Vegetables", "price": 52, "image": "https://res.cloudinary.com/dfqqacmzv/image/upload/v1760772726/s10_osci6o.png" },
  { "id": 11, "name": "JACK FRUIT", "category": "Vegetables", "price": 40, "image": "https://res.cloudinary.com/dfqqacmzv/image/upload/v1760772726/s11_pu7zz9.png" },
  { "id": 12, "name": "CAULI FLOWER", "category": "Vegetables", "price": 28, "image": "https://res.cloudinary.com/dfqqacmzv/image/upload/v1760772726/s12_um43uv.png" },
  { "id": 13, "name": "RED SPINACH", "category": "Vegetables", "price": 25, "image": "https://res.cloudinary.com/dfqqacmzv/image/upload/v1760803440/fresh-red-spinach-1649157687-6273035_s9j4jq.jpg" },
  { "id": 14, "name": "DRUMSTICK", "category": "Vegetables", "price": 60, "image": "https://res.cloudinary.com/dfqqacmzv/image/upload/v1760772727/s14_jqkhpi.png" },
  { "id": 15, "name": "CUCUMBER", "category": "Vegetables", "price": 29, "image": "https://res.cloudinary.com/dfqqacmzv/image/upload/v1760772727/s15_vz51xk.png" },
  { "id": 16, "name": "PUMPKIN", "category": "Vegetables", "price": 20, "image": "https://res.cloudinary.com/dfqqacmzv/image/upload/v1760772727/s16_rt8yrp.png" },
  { "id": 17, "name": "SWEET POTATO", "category": "Vegetables", "price": 28, "image": "https://res.cloudinary.com/dfqqacmzv/image/upload/v1760772727/s17_onqh6s.png" },
  { "id": 18, "name": "SPINACH", "category": "Vegetables", "price": 25, "image": "https://res.cloudinary.com/dfqqacmzv/image/upload/v1760772727/s18_vatfra.png" },
  { "id": 19, "name": "TURNIP", "category": "Vegetables", "price": 30, "image": "https://res.cloudinary.com/dfqqacmzv/image/upload/v1760772732/s19_havzgt.png" },
  { "id": 20, "name": "MUSHROOM", "category": "Vegetables", "price": 120, "image": "https://res.cloudinary.com/dfqqacmzv/image/upload/v1760772732/s20_yjlmpk.png" },
  { "id": 21, "name": "CLUSTER BEANS", "category": "Vegetables", "price": 50, "image": "https://res.cloudinary.com/dfqqacmzv/image/upload/v1760772733/s21_iw2irt.png" },
  { "id": 22, "name": "AMARANTH LEAVES", "category": "Vegetables", "price": 22, "image": "https://res.cloudinary.com/dfqqacmzv/image/upload/v1760772735/s22_ywpz3b.png" },
  { "id": 23, "name": "BRINJAL", "category": "Vegetables", "price": 35, "image": "https://res.cloudinary.com/dfqqacmzv/image/upload/v1760772734/s23_gvqtyo.png" },
  { "id": 24, "name": "RADISH", "category": "Vegetables", "price": 26, "image": "https://res.cloudinary.com/dfqqacmzv/image/upload/v1760772733/s24_rasg9d.png" },
  { "id": 25, "name": "ASH GOURD", "category": "Vegetables", "price": 20, "image": "https://res.cloudinary.com/dfqqacmzv/image/upload/v1760772734/s25_tlwnnp.png" },
  { "id": 26, "name": "BITTER GOURD", "category": "Vegetables", "price": 20, "image": "https://res.cloudinary.com/dfqqacmzv/image/upload/v1760772734/s26_wybous.png" },
  { "id": 27, "name": "SNAKE GOURD", "category": "Vegetables", "price": 33, "image": "https://res.cloudinary.com/dfqqacmzv/image/upload/v1760772739/s27_vdkqdw.png" },
  { "id": 28, "name": "BOTTLE GOURD", "category": "Vegetables", "price": 25, "image": "https://res.cloudinary.com/dfqqacmzv/image/upload/v1760772739/s28_m7dvpf.png" },
  { "id": 29, "name": "SPONGE GOURD", "category": "Vegetables", "price": 30, "image": "https://res.cloudinary.com/dfqqacmzv/image/upload/v1760772739/s29_ltahzl.png" },
  { "id": 30, "name": "CARROT", "category": "Vegetables", "price": 44, "image": "https://res.cloudinary.com/dfqqacmzv/image/upload/v1760772739/s30_stk5ew.png" },
  { "id": 31, "name": "RAW PAPAYA", "category": "Vegetables", "price": 25, "image": "https://res.cloudinary.com/dfqqacmzv/image/upload/v1760772739/s31_wgapjc.png" },
  { "id": 32, "name": "TENDLI", "category": "Vegetables", "price": 55, "image": "https://res.cloudinary.com/dfqqacmzv/image/upload/v1760772740/s32_kf58b6.png" },
  { "id": 33, "name": "GREEN CAPSICUM", "category": "Vegetables", "price": 42, "image": "https://res.cloudinary.com/dfqqacmzv/image/upload/v1760772742/s33_knav8v.png" },
  { "id": 34, "name": "APPLE GOURD", "category": "Vegetables", "price": 26, "image": "https://res.cloudinary.com/dfqqacmzv/image/upload/v1760772745/s34_vw2lzy.png" },
  { "id": 35, "name": "ELEPHANT FOOT YAM", "category": "Vegetables", "price": 40, "image": "https://res.cloudinary.com/dfqqacmzv/image/upload/v1760772745/s35_klrfsr.png" }
]
